monkey/__init__.py
monkey/crawler/__init__.py
monkey/crawler/crawlers/__init__.py
monkey/crawler/crawlers/mongodb.py
monkey.crawler.pymongo-0.0.1.dev2.dist-info/LICENSE.txt
monkey.crawler.pymongo-0.0.1.dev2.dist-info/METADATA
monkey.crawler.pymongo-0.0.1.dev2.dist-info/WHEEL
monkey.crawler.pymongo-0.0.1.dev2.dist-info/top_level.txt
monkey.crawler.pymongo-0.0.1.dev2.dist-info/RECORD
